gslocalizator/__init__.py
gslocalizator/localizator.py
gslocalizator/parser.py
gslocalizator/sheet_tran_task.py
gslocalizator/string_file.py
gslocalizator-1.0.0.dist-info/METADATA
gslocalizator-1.0.0.dist-info/WHEEL
gslocalizator-1.0.0.dist-info/top_level.txt
gslocalizator-1.0.0.dist-info/RECORD
