Metadata-Version: 2.1
Name: gslocalizator
Version: 1.0.0
Summary: update localization texts from google doc
Home-page: https://github.com/ovotop/gslocalizator
Author: JeffreyCao
Author-email: jeffreycao1024@gmail.com
License: MIT Licence
Keywords: google sheet,localization,l10n,i18n
Platform: any
Classifier: Programming Language :: Python :: 3
Classifier: License :: OSI Approved :: MIT License
Classifier: Operating System :: OS Independent
Requires-Python: >=3.6
Requires-Dist: ezutils
Requires-Dist: google-api-python-client
Requires-Dist: google-auth-httplib2
Requires-Dist: google-auth-oauthlib
